ctk_sidebar-0.2.4.dist-info/licenses/LICENSE
ctksidebar/__init__.py
ctksidebar/item.py
ctksidebar/menu.py
ctksidebar/nav.py
ctksidebar/theme.py
ctksidebar/util.py
ctk_sidebar-0.2.4.dist-info/METADATA
ctk_sidebar-0.2.4.dist-info/WHEEL
ctk_sidebar-0.2.4.dist-info/top_level.txt
ctk_sidebar-0.2.4.dist-info/RECORD
