Metadata-Version: 2.4
Name: ctk-sidebar
Version: 0.2.4
Summary: A modern sidebar navigation control for CustomTkinter
Author: Anthony Bernaert
License-Expression: MIT
Project-URL: Homepage, https://github.com/anthony-bernaert/ctk-sidebar
Project-URL: Repository, https://github.com/anthony-bernaert/ctk-sidebar
Project-URL: Issues, https://github.com/anthony-bernaert/ctk-sidebar/issues
Classifier: Operating System :: OS Independent
Classifier: Programming Language :: Python :: 3 :: Only
Requires-Python: >=3.9
License-File: LICENSE
Requires-Dist: pillow
Requires-Dist: customtkinter
Dynamic: license-file
